cmaps/__init__.py
cmaps/_version.py
cmaps/cmaps.py
cmaps/colormap.py
cmaps/show_map_helper.py
cmaps/colormaps/cmcrameri/acton.rgb
cmaps/colormaps/cmcrameri/actonS.rgb
cmaps/colormaps/cmcrameri/bam.rgb
cmaps/colormaps/cmcrameri/bamO.rgb
cmaps/colormaps/cmcrameri/bamako.rgb
cmaps/colormaps/cmcrameri/bamakoS.rgb
cmaps/colormaps/cmcrameri/batlow.rgb
cmaps/colormaps/cmcrameri/batlowK.rgb
cmaps/colormaps/cmcrameri/batlowKS.rgb
cmaps/colormaps/cmcrameri/batlowS.rgb
cmaps/colormaps/cmcrameri/batlowW.rgb
cmaps/colormaps/cmcrameri/batlowWS.rgb
cmaps/colormaps/cmcrameri/berlin.rgb
cmaps/colormaps/cmcrameri/bilbao.rgb
cmaps/colormaps/cmcrameri/bilbaoS.rgb
cmaps/colormaps/cmcrameri/broc.rgb
cmaps/colormaps/cmcrameri/brocO.rgb
cmaps/colormaps/cmcrameri/buda.rgb
cmaps/colormaps/cmcrameri/budaS.rgb
cmaps/colormaps/cmcrameri/bukavu.rgb
cmaps/colormaps/cmcrameri/cork.rgb
cmaps/colormaps/cmcrameri/corkO.rgb
cmaps/colormaps/cmcrameri/davos.rgb
cmaps/colormaps/cmcrameri/davosS.rgb
cmaps/colormaps/cmcrameri/devon.rgb
cmaps/colormaps/cmcrameri/devonS.rgb
cmaps/colormaps/cmcrameri/fes.rgb
cmaps/colormaps/cmcrameri/glasgow.rgb
cmaps/colormaps/cmcrameri/glasgowS.rgb
cmaps/colormaps/cmcrameri/grayC.rgb
cmaps/colormaps/cmcrameri/grayCS.rgb
cmaps/colormaps/cmcrameri/hawaii.rgb
cmaps/colormaps/cmcrameri/hawaiiS.rgb
cmaps/colormaps/cmcrameri/imola.rgb
cmaps/colormaps/cmcrameri/imolaS.rgb
cmaps/colormaps/cmcrameri/lajolla.rgb
cmaps/colormaps/cmcrameri/lajollaS.rgb
cmaps/colormaps/cmcrameri/lapaz.rgb
cmaps/colormaps/cmcrameri/lapazS.rgb
cmaps/colormaps/cmcrameri/lipari.rgb
cmaps/colormaps/cmcrameri/lipariS.rgb
cmaps/colormaps/cmcrameri/lisbon.rgb
cmaps/colormaps/cmcrameri/managua.rgb
cmaps/colormaps/cmcrameri/navia.rgb
cmaps/colormaps/cmcrameri/naviaS.rgb
cmaps/colormaps/cmcrameri/nuuk.rgb
cmaps/colormaps/cmcrameri/nuukS.rgb
cmaps/colormaps/cmcrameri/oleron.rgb
cmaps/colormaps/cmcrameri/oslo.rgb
cmaps/colormaps/cmcrameri/osloS.rgb
cmaps/colormaps/cmcrameri/roma.rgb
cmaps_devin-2.1.3.dist-info/LICENSE
cmaps_devin-2.1.3.dist-info/METADATA
cmaps_devin-2.1.3.dist-info/WHEEL
cmaps_devin-2.1.3.dist-info/top_level.txt
cmaps_devin-2.1.3.dist-info/RECORD
